google_play_reader/__init__.py
google_play_reader/models.py
google_play_reader-0.0.1.dev16.dist-info/DESCRIPTION.rst
google_play_reader-0.0.1.dev16.dist-info/METADATA
google_play_reader-0.0.1.dev16.dist-info/RECORD
google_play_reader-0.0.1.dev16.dist-info/WHEEL
google_play_reader-0.0.1.dev16.dist-info/metadata.json
google_play_reader-0.0.1.dev16.dist-info/pbr.json
google_play_reader-0.0.1.dev16.dist-info/top_level.txt
