Metadata-Version: 2.0
Name: google-play-reader
Version: 0.0.1.dev16
Summary: Tool to get information about Android apps on Google Play
Home-page: https://luiscruz.github.io/
Author: Luis Cruz
Author-email: luismirandacruz@gmail.com
License: MIT
Platform: UNKNOWN
Classifier: Development Status :: 4 - Beta
Classifier: Environment :: Plugins
Classifier: Intended Audience :: Science/Research
Classifier: Intended Audience :: Developers
Classifier: Intended Audience :: Information Technology
Classifier: Operating System :: OS Independent
Classifier: Programming Language :: Python
Classifier: License :: OSI Approved :: MIT License
Classifier: Topic :: Software Development :: Libraries
Classifier: Topic :: Scientific/Engineering
Classifier: Topic :: Utilities
Requires-Dist: requests
Requires-Dist: lxml
